dvc_pandas/__init__.py
dvc_pandas/dataset.py
dvc_pandas/dvc.py
dvc_pandas/py.typed
dvc_pandas/repository.py
dvc_pandas/utils.py
dvc_pandas-0.3.3.dist-info/METADATA
dvc_pandas-0.3.3.dist-info/WHEEL
dvc_pandas-0.3.3.dist-info/licenses/LICENSE
dvc_pandas-0.3.3.dist-info/RECORD
