Metadata-Version: 2.3
Name: dvc-pandas
Version: 0.3.3
Summary: Wrapper for DVC and git to easily fetch Polars dataframes
Project-URL: Repository, https://github.com/kausaltech/dvc-pandas
Author-email: Bernhard Bliem <bernhard.bliem@kausal.tech>, Juha Yrjölä <juha.yrjola@kausal.tech>
Classifier: Development Status :: 4 - Beta
Classifier: Programming Language :: Python
Requires-Python: >=3.12
Requires-Dist: appdirs>=1.4.4
Requires-Dist: dvc-s3>=3.2.0
Requires-Dist: dvc>=3.54.1
Requires-Dist: filelock>=3.15.4
Requires-Dist: pandas>=2.2.2
Requires-Dist: pint-pandas>=0.6.2
Requires-Dist: polars>=1.5.0
Requires-Dist: pyarrow>=17.0.0
Requires-Dist: pygit2>=1.15.1
Requires-Dist: python-snappy>=0.7.2
Requires-Dist: ruamel-yaml>=0.18.6
